jaime38130
