Metadata-Version: 2.1
Name: jaime38130
Version: 1.1
Summary: I needed colors
Home-page: https://github.com/JaimeSilva/jaime38130.git
Download-URL: https://github.com/JaimeSilva/jaime38130/archive/refs/tags/v_11.tar.gz
Author: Jaime Silva
Author-email: jaimedcsilva@hotmail.com
License: MIT
Keywords: SOME,MEANINGFULL,COLORS
Classifier: Development Status :: 3 - Alpha
Classifier: Intended Audience :: Developers
Classifier: Topic :: Software Development :: Build Tools
Classifier: License :: OSI Approved :: MIT License
Classifier: Programming Language :: Python :: 3
Classifier: Programming Language :: Python :: 3.4
Classifier: Programming Language :: Python :: 3.5
Classifier: Programming Language :: Python :: 3.6
Classifier: Programming Language :: Python :: 3.8
Classifier: Programming Language :: Python :: 3.10
License-File: LICENSE.txt
Requires-Dist: colorama
